simple_smartsheet/__init__.py
simple_smartsheet/config.py
simple_smartsheet/constants.py
simple_smartsheet/crud.py
simple_smartsheet/exceptions.py
simple_smartsheet/models/__init__.py
simple_smartsheet/models/base.py
simple_smartsheet/models/cell.py
simple_smartsheet/models/column.py
simple_smartsheet/models/extra.py
simple_smartsheet/models/report.py
simple_smartsheet/models/row.py
simple_smartsheet/models/sheet.py
simple_smartsheet/smartsheet.py
simple_smartsheet/types.py
simple_smartsheet/utils.py
simple_smartsheet-0.4.2.dist-info/LICENSE
simple_smartsheet-0.4.2.dist-info/WHEEL
simple_smartsheet-0.4.2.dist-info/METADATA
simple_smartsheet-0.4.2.dist-info/RECORD
