Metadata-Version: 2.1
Name: simple-smartsheet
Version: 0.4.2
Summary: Python library to interact with Smartsheet API
Home-page: https://github.com/dmfigol/simple-smartsheet
License: MIT
Keywords: smartsheet
Author: Dmitry Figol
Author-email: git@dmfigol.me
Requires-Python: >=3.6
Classifier: Development Status :: 4 - Beta
Classifier: Intended Audience :: Developers
Classifier: License :: OSI Approved :: MIT License
Classifier: Programming Language :: Python :: 3
Classifier: Programming Language :: Python :: 3 :: Only
Classifier: Programming Language :: Python :: 3.6
Classifier: Programming Language :: Python :: 3.7
Classifier: Topic :: Software Development :: Libraries :: Python Modules
Requires-Dist: aiohttp
Requires-Dist: attrs
Requires-Dist: cattrs
Requires-Dist: marshmallow (>=3.0.0rc9)
Requires-Dist: mypy-extensions
Requires-Dist: requests
Project-URL: Repository, https://github.com/dmfigol/simple-smartsheet
